{
  "en": {
    "lesli": {
      "application": {
        "navigation_logout": "Logout",
        "navigation_my_profile": "My profile"
      },
      "dashboards": {
        "column_default": "Default",
        "column_name": "Name",
        "title": "Dashboards",
        "view_add_component": "Add component"
      },
      "shared": {
        "button_add_new": "Add new",
        "button_delete": "Delete",
        "button_edit": "Edit",
        "button_list": "List",
        "button_reload": "Reload",
        "button_save": "Save",
        "button_settings": "Settings",
        "button_show": "Show",
        "message_operation_error": "Operation failed. Please try again.",
        "message_operation_success": "Operation completed successfully",
        "toolbar_search": "Search...",
        "view_discussions": "Discussions",
        "view_files": "Files",
        "view_quick_actions": "Quick actions",
        "view_status_active": "Active",
        "view_status_inactive": "Inactive"
      },
      "users/sessions": {
        "view_username": "Username"
      }
    }
  },
  "es": {
    "lesli": {
      "application": {
        "navigation_logout": "Cerrar sesión",
        "navigation_my_profile": "Mi perfil"
      },
      "dashboards": {
        "column_default": "Default",
        "column_name": "Nombre",
        "title": "Dashboards",
        "view_add_component": "Agregar componente"
      },
      "shared": {
        "button_add_new": "Agregar nuevo",
        "button_delete": "Eliminar",
        "button_edit": "Editar",
        "button_list": "Lista",
        "button_reload": "Recargar",
        "button_save": "Guardar",
        "button_settings": "Configuración",
        "button_show": "Ver",
        "message_operation_error": "Operación fallida. Por favor, inténtelo de nuevo.",
        "message_operation_success": "Operacion realizada satisfactoriamente",
        "toolbar_search": "Buscar...",
        "view_discussions": "Discusiones",
        "view_files": "Archivos",
        "view_quick_actions": "Acciones rapidas",
        "view_status_active": "Activo",
        "view_status_inactive": "Inactivo"
      },
      "users/sessions": {
        "view_username": "Usuario"
      }
    }
  },
  "fr": {
    "lesli": {
      "application": {
        "navigation_logout": ":lesli.application.navigation_logout:",
        "navigation_my_profile": ":lesli.application.navigation_my_profile:"
      },
      "dashboards": {
        "column_default": ":lesli.dashboards.column_default:",
        "column_name": ":lesli.dashboards.column_name:",
        "title": ":lesli.dashboards.title:",
        "view_add_component": ":lesli.dashboards.view_add_component:"
      },
      "shared": {
        "button_add_new": ":lesli.shared.button_add_new:",
        "button_delete": ":lesli.shared.button_delete:",
        "button_edit": ":lesli.shared.button_edit:",
        "button_list": ":lesli.shared.button_list:",
        "button_reload": ":lesli.shared.button_reload:",
        "button_save": ":lesli.shared.button_save:",
        "button_settings": ":lesli.shared.button_settings:",
        "button_show": ":lesli.shared.button_show:",
        "message_operation_error": ":lesli.shared.message_operation_error:",
        "message_operation_success": ":lesli.shared.message_operation_success:",
        "toolbar_search": ":lesli.shared.toolbar_search:",
        "view_discussions": ":lesli.shared.view_discussions:",
        "view_files": ":lesli.shared.view_files:",
        "view_quick_actions": ":lesli.shared.view_quick_actions:",
        "view_status_active": ":lesli.shared.view_status_active:",
        "view_status_inactive": ":lesli.shared.view_status_inactive:"
      },
      "users/sessions": {
        "view_username": ":lesli.users/sessions.view_username:"
      }
    }
  },
  "it": {
    "lesli": {
      "application": {
        "navigation_logout": ":lesli.application.navigation_logout:",
        "navigation_my_profile": ":lesli.application.navigation_my_profile:"
      },
      "dashboards": {
        "column_default": ":lesli.dashboards.column_default:",
        "column_name": ":lesli.dashboards.column_name:",
        "title": ":lesli.dashboards.title:",
        "view_add_component": ":lesli.dashboards.view_add_component:"
      },
      "shared": {
        "button_add_new": ":lesli.shared.button_add_new:",
        "button_delete": ":lesli.shared.button_delete:",
        "button_edit": ":lesli.shared.button_edit:",
        "button_list": ":lesli.shared.button_list:",
        "button_reload": ":lesli.shared.button_reload:",
        "button_save": ":lesli.shared.button_save:",
        "button_settings": ":lesli.shared.button_settings:",
        "button_show": ":lesli.shared.button_show:",
        "message_operation_error": ":lesli.shared.message_operation_error:",
        "message_operation_success": ":lesli.shared.message_operation_success:",
        "toolbar_search": ":lesli.shared.toolbar_search:",
        "view_discussions": ":lesli.shared.view_discussions:",
        "view_files": ":lesli.shared.view_files:",
        "view_quick_actions": ":lesli.shared.view_quick_actions:",
        "view_status_active": ":lesli.shared.view_status_active:",
        "view_status_inactive": ":lesli.shared.view_status_inactive:"
      },
      "users/sessions": {
        "view_username": ":lesli.users/sessions.view_username:"
      }
    }
  },
  "pt": {
    "lesli": {
      "application": {
        "navigation_logout": ":lesli.application.navigation_logout:",
        "navigation_my_profile": ":lesli.application.navigation_my_profile:"
      },
      "dashboards": {
        "column_default": ":lesli.dashboards.column_default:",
        "column_name": ":lesli.dashboards.column_name:",
        "title": ":lesli.dashboards.title:",
        "view_add_component": ":lesli.dashboards.view_add_component:"
      },
      "shared": {
        "button_add_new": ":lesli.shared.button_add_new:",
        "button_delete": ":lesli.shared.button_delete:",
        "button_edit": ":lesli.shared.button_edit:",
        "button_list": ":lesli.shared.button_list:",
        "button_reload": ":lesli.shared.button_reload:",
        "button_save": ":lesli.shared.button_save:",
        "button_settings": ":lesli.shared.button_settings:",
        "button_show": ":lesli.shared.button_show:",
        "message_operation_error": ":lesli.shared.message_operation_error:",
        "message_operation_success": ":lesli.shared.message_operation_success:",
        "toolbar_search": ":lesli.shared.toolbar_search:",
        "view_discussions": ":lesli.shared.view_discussions:",
        "view_files": ":lesli.shared.view_files:",
        "view_quick_actions": ":lesli.shared.view_quick_actions:",
        "view_status_active": ":lesli.shared.view_status_active:",
        "view_status_inactive": ":lesli.shared.view_status_inactive:"
      },
      "users/sessions": {
        "view_username": ":lesli.users/sessions.view_username:"
      }
    }
  }
}